border_patrol/__init__.py
border_patrol/with_log_debug.py
border_patrol/with_log_error.py
border_patrol/with_log_info.py
border_patrol/with_log_warning.py
border_patrol/with_print_stderr.py
border_patrol/with_print_stdout.py
border_patrol-1.0.1.dist-info/AUTHORS.rst
border_patrol-1.0.1.dist-info/LICENSE.txt
border_patrol-1.0.1.dist-info/METADATA
border_patrol-1.0.1.dist-info/WHEEL
border_patrol-1.0.1.dist-info/top_level.txt
border_patrol-1.0.1.dist-info/RECORD
